df_csv_excel/__init__.py
df_csv_excel/fe_functions.py
df_csv_excel/models.py
df_csv_excel/plot_data.py
df_csv_excel/read_data.py
df_csv_excel-0.1.43.dist-info/LICENSE
df_csv_excel-0.1.43.dist-info/METADATA
df_csv_excel-0.1.43.dist-info/WHEEL
df_csv_excel-0.1.43.dist-info/top_level.txt
df_csv_excel-0.1.43.dist-info/RECORD
