Metadata-Version: 2.1
Name: df-csv-excel
Version: 0.1.43
Summary: Commonly used functions for Data Scientists
Home-page: https://github.com/cheerzhang/read_csv_excel
Author: ZhangLe
Author-email: zhangle@gmail.com
License: UNKNOWN
Project-URL: Bug Tracker, https://github.com/cheerzhang/read_csv_excel/issues
Platform: UNKNOWN
Classifier: Programming Language :: Python :: 3
Classifier: License :: OSI Approved :: MIT License
Classifier: Operating System :: OS Independent
Requires-Python: >=3.9
License-File: LICENSE
Requires-Dist: pandas >=0.25.1
Requires-Dist: numpy >=1.21.5
Requires-Dist: plotly >=5.18.0
Requires-Dist: matplotlib >=3.7.1
Requires-Dist: SciPy >=1.11.4
Requires-Dist: cdifflib >=1.2.6
